{
  "updated": "2026-07-08 11:50 UTC",
  "count": 42,
  "deals": [
    {
      "id": "Slickdeals-562345",
      "title": "Klein Tools 11-in-1 Multi Bit Screwdriver & Nut Driver w/ Cushion Grip Handle $12",
      "description": "Amazon.com has Klein Tools 32500 11-in-1 Screwdriver/Nut Driver Set, 8 Bits (Phillips, Slotted, Torx, Square), 3 Nut Driver Sizes, Cushion Grip Handle for $11.98. \nShipping is free with Prime or on...",
      "link": "https://slickdeals.net/f/19734996-11-in-1-klein-tools-multi-bit-screwdriver-nut-driver-with-cushion-grip-handle-32500-11-98-free-s-h-w-prime-or-35?utm_source=rss&utm_content=fp&utm_medium=RSS2",
      "source": "Slickdeals",
      "retailer": "Amazon",
      "category": "Tools & Hardware",
      "discount": null,
      "date_iso": "2026-07-08T11:48:40+00:00",
      "date_display": "Jul 08, 11:48 AM"
    },
    {
      "id": "Slickdeals-193011",
      "title": "Odoland 2-Burner 17000 BTU Portable Propane Gas Camping Stove $45 + Free S&H",
      "description": "Unicorn US via Amazon [amazon.com] has *Odoland Portable 2-Burner 17000 BTU Propane Camping Stove* on sale for $89.99 - 50% with promo code EJOSK5G3= *$44.99*. *Shipping is free.*",
      "link": "https://slickdeals.net/f/19732788-odoland-portable-2-burner-17000-btu-propane-camping-stove-44-99-free-shipping?utm_source=rss&utm_content=fp&utm_medium=RSS2",
      "source": "Slickdeals",
      "retailer": "Amazon",
      "category": "Outdoor & Lawn",
      "discount": null,
      "date_iso": "2026-07-08T11:41:15+00:00",
      "date_display": "Jul 08, 11:41 AM"
    },
    {
      "id": "Slickdeals-192443",
      "title": "Mountain Hardwear Men Ap Pant (Select Sizes) $17 + Free S&H w/ Amazon Prime",
      "description": "*Woot!* [woot.com] has *Mountain Hardwear Men Ap Pant* for *$16.99*. \n*Shipping is free* for Amazon Prime Members (must login with your Amazon account and select a shipping address in order for Woot..",
      "link": "https://slickdeals.net/f/19735122-16-99-mountain-hardwear-men-ap-pant-at-woot?utm_source=rss&utm_content=fp&utm_medium=RSS2",
      "source": "Slickdeals",
      "retailer": "Amazon",
      "category": "Clothing & Shoes",
      "discount": null,
      "date_iso": "2026-07-08T09:14:26+00:00",
      "date_display": "Jul 08, 09:14 AM"
    },
    {
      "id": "Slickdeals-512443",
      "title": "BEVA 150PSI Portable Air Compressor w/ Digital Pressure Gauge & LED Light $15",
      "description": "Amazon has BEVA Tire Inflator Portable Air Compressor, Fast Inflation Bike Pump with Digital Pressure Gauge and LED Light, for $ 14.99 with code *NJR9Q9DN * \n \nhttps://www.amazon.com/dp/B0GXK7GMKQ",
      "link": "https://slickdeals.net/f/19731810-beva-tire-inflator-portable-air-compressor-fast-inflation-bike-pump-with-digital-pressure-gauge-and-led-light-150psi-portable-air-pump-14-99?utm_source=rss&utm_content=fp&utm_medium=RSS2",
      "source": "Slickdeals",
      "retailer": "Amazon",
      "category": "Tools & Hardware",
      "discount": null,
      "date_iso": "2026-07-08T08:44:16+00:00",
      "date_display": "Jul 08, 08:44 AM"
    },
    {
      "id": "DealNews Tools-787954",
      "title": "Meifigno MagSafe Car Phone Mount for $10 + free shipping w/ Prime",
      "description": "Meifigno's MagSafe car mount snaps your iPhone onto a vent, dashboard, or windshield and holds it securely without plugging anything in, which is useful if you rely on your phone for navigation and do",
      "link": "https://www.dealnews.com/products/Meifigno/Meifigno-Magsafe-Car-Mount/498986.html?iref=rss-c238",
      "source": "DealNews Tools",
      "retailer": "Amazon",
      "category": "Home & Garden",
      "discount": null,
      "date_iso": "2026-07-08T07:31:32-04:00",
      "date_display": "Jul 08, 07:31 AM"
    },
    {
      "id": "Slickdeals-693282",
      "title": "3-Pk Men's Bonds Underwear Anti-Chafing Boxer Brief (various colors/sizes) $9 + Free S&H w/ Amazon Prime",
      "description": "*Woot!* [woot.com] has *Bonds Men Underwear Anti-chafing Boxer Briefs* for *$8.99*. \n*Shipping is free* for Amazon Prime Members (must login with your Amazon account and select a shipping address in..",
      "link": "https://slickdeals.net/f/19730679-8-99-bonds-men-underwear-anti-chafing-boxer-briefs-at-woot?utm_source=rss&utm_content=fp&utm_medium=RSS2",
      "source": "Slickdeals",
      "retailer": "Amazon",
      "category": "Clothing & Shoes",
      "discount": null,
      "date_iso": "2026-07-08T07:10:05+00:00",
      "date_display": "Jul 08, 07:10 AM"
    },
    {
      "id": "DealNews-538511",
      "title": "Anker Nano 45W Foldable USB-C GaN Charger for $26 + free shipping w/ Prime",
      "description": "This Anker Nano charger is $25.99, down from $39.99, and matches its all-time low price on Amazon. It delivers up to 45W of fast charging, folds down to a compact size, and includes a smart display th",
      "link": "https://www.dealnews.com/products/Anker/Anker-Nano-45-W-Foldable-USB-C-Ga-N-Charger/504983.html?iref=rss-c142",
      "source": "DealNews",
      "retailer": "Amazon",
      "category": "Electronics & Tech",
      "discount": null,
      "date_iso": "2026-07-08T07:04:29-04:00",
      "date_display": "Jul 08, 07:04 AM"
    },
    {
      "id": "DealNews Tools-460220",
      "title": "Bumbee Tailgate Bike Pad for $29 + free shipping",
      "description": "At Amazon, get the Bumbee Tailgate Bike Pad for $29 when you clip the on-page coupon. It's the best price Amazon has charged for this tailgate bike pad. This pad holds two bikes at once while protecti",
      "link": "https://www.dealnews.com/Bumbee-Tailgate-Bike-Pad-for-29-free-shipping/21888024.html?iref=rss-c238",
      "source": "DealNews Tools",
      "retailer": "Amazon",
      "category": "Home & Garden",
      "discount": null,
      "date_iso": "2026-07-08T06:06:43-04:00",
      "date_display": "Jul 08, 06:06 AM"
    },
    {
      "id": "Slickdeals-190957",
      "title": "Select Locations: AMD Ryzen 9 7900X 4.7 GHz 12-Core 24-Thread Unlocked Desktop CPU $247.45 + Free S&H",
      "description": "Amazon [amazon.com] has for select accounts: *AMD Ryzen 9 7900X 12-Core 24-Thread Unlocked Desktop Processor* for $274.95 - 10% when you clip the coupon on product page* = $247.45*. *Shipping is...",
      "link": "https://slickdeals.net/f/19733658-select-accounts-amd-ryzen-9-7900x-12-core-24-thread-unlocked-desktop-processor-247-free-shipping?utm_source=rss&utm_content=fp&utm_medium=RSS2",
      "source": "Slickdeals",
      "retailer": "Amazon",
      "category": "Electronics & Tech",
      "discount": null,
      "date_iso": "2026-07-08T05:55:57+00:00",
      "date_display": "Jul 08, 05:55 AM"
    },
    {
      "id": "DealNews Tools-338356",
      "title": "WorkPro Garage Wall Protector 4-Pack for $16 + free shipping w/ Prime",
      "description": "At Amazon, get this WorkPro Garage Wall Protector 4-Pack for $16. It's the best price we could find by $9 and the second-best deal we've seen for this 4-pack. The set includes four 1.18\" thick NBR foa",
      "link": "https://www.dealnews.com/Work-Pro-Garage-Wall-Protector-4-Pack-for-16-free-shipping-w-Prime/21888008.html?iref=rss-c238",
      "source": "DealNews Tools",
      "retailer": "Amazon",
      "category": "Home & Garden",
      "discount": null,
      "date_iso": "2026-07-08T05:05:01-04:00",
      "date_display": "Jul 08, 05:05 AM"
    },
    {
      "id": "DealNews-439440",
      "title": "Kactoily 7-in-1 WiFi Smart Pool Water Monitor for $169 + free shipping",
      "description": "Monitors chlorine, pH, ORP, salinity, TDS, temperature, and conductivity in real time through a smartphone app, which suits pool owners who want ongoing water quality data without buying separate test",
      "link": "https://www.dealnews.com/Kactoily-7-in-1-Wi-Fi-Smart-Pool-Water-Monitor-for-169-free-shipping/21887988.html?iref=rss-c142",
      "source": "DealNews",
      "retailer": "Amazon",
      "category": "Electronics & Tech",
      "discount": null,
      "date_iso": "2026-07-08T04:22:55-04:00",
      "date_display": "Jul 08, 04:22 AM"
    },
    {
      "id": "DealNews-796975",
      "title": "Unlocked Motorola Moto G Power 6.8\" 128GB Smartphone for $200 + free shipping",
      "description": "At $200, this Moto G Power is $100 off and at Amazon's all-time low. This model pairs a 5,000mAh battery with a 6.8\" 120Hz display, both features that go beyond what's typical for phones at this price",
      "link": "https://www.dealnews.com/Unlocked-Motorola-Moto-G-Power-6-8-128-GB-Smartphone-for-200-free-shipping/21887976.html?iref=rss-c142",
      "source": "DealNews",
      "retailer": "Amazon",
      "category": "Electronics & Tech",
      "discount": 100,
      "date_iso": "2026-07-08T03:39:34-04:00",
      "date_display": "Jul 08, 03:39 AM"
    },
    {
      "id": "DealNews-205728",
      "title": "Like-New Amazon Devices Sale at Woot for From $20 + free shipping w/ Prime",
      "description": "This Woot sale covers Like-New Amazon smart devices without power adapters or accessories, such as the Amazon Echo Dot (2022) at $24.99 and the Amazon Echo Show 5 Kids at $49.99. The Amazon Echo Auto ",
      "link": "https://www.dealnews.com/Like-New-Amazon-Devices-Sale-at-Woot-for-From-20-free-shipping-w-Prime/21887960.html?iref=rss-c142",
      "source": "DealNews",
      "retailer": "Amazon",
      "category": "Electronics & Tech",
      "discount": null,
      "date_iso": "2026-07-08T02:21:06-04:00",
      "date_display": "Jul 08, 02:21 AM"
    },
    {
      "id": "DealNews-569668",
      "title": "Deluxe Portable CD Player for $10 + free shipping w/ Prime",
      "description": "Woot offers the Deluxe Portable CD Player in three colors for $9.99, a small price to pay for nostalgia.\u00a0 You'd pay closer to $30 elsewhere.\u00a0 Shipping is free for Prime members.\u00a0 Deal ends July 10th. ",
      "link": "https://www.dealnews.com/Deluxe-Portable-CD-Player-for-10-free-shipping-w-Prime/21886353.html?iref=rss-c142",
      "source": "DealNews",
      "retailer": "Amazon",
      "category": "Electronics & Tech",
      "discount": null,
      "date_iso": "2026-07-07T21:23:22-04:00",
      "date_display": "Jul 07, 09:23 PM"
    },
    {
      "id": "DealNews-544897",
      "title": "5000mAh Magnetic Wireless Portable Charger for $19 + free shipping w/ Prime",
      "description": "This magnetic power bank is at its lowest recorded price on Amazon. At $18.98, that's $12 off. Shipping is free for Prime members.\u00a0 Buy Now at Amazon      Features     5,000mAh battery capacity   Magn",
      "link": "https://www.dealnews.com/products/5000-m-Ah-Magnetic-Wireless-Portable-Charger/506683.html?iref=rss-c142",
      "source": "DealNews",
      "retailer": "Amazon",
      "category": "Electronics & Tech",
      "discount": 12,
      "date_iso": "2026-07-07T19:14:54-04:00",
      "date_display": "Jul 07, 07:14 PM"
    },
    {
      "id": "DealNews Tools-731011",
      "title": "Airmoto Portable Tire Inflator Air Compressor for $59 + free shipping",
      "description": "This tire inflator is $59.49 at Amazon. That's a savings of $11. Shipping is free.\u00a0 Buy Now at Amazon      Features     Inflates tires up to 120 PSI   Auto shut-off once target pressure is reached   D",
      "link": "https://www.dealnews.com/products/Airmoto-Portable-Tire-Inflator-Air-Compressor/506673.html?iref=rss-c238",
      "source": "DealNews Tools",
      "retailer": "Amazon",
      "category": "Home & Garden",
      "discount": null,
      "date_iso": "2026-07-07T17:01:11-04:00",
      "date_display": "Jul 07, 05:01 PM"
    },
    {
      "id": "DealNews Tools-106658",
      "title": "Miracase Air Vent Cell Phone Car Mount for $13 + free shipping w/ Prime",
      "description": "This Miracase car mount is $12.98 at Amazon. That's a 35% savings. Shipping is free for Prime members.\u00a0 Buy Now at Amazon      Features     Metal hook clip attaches to horizontal or vertical air vent ",
      "link": "https://www.dealnews.com/Miracase-Air-Vent-Cell-Phone-Car-Mount-for-13-free-shipping-w-Prime/21886309.html?iref=rss-c238",
      "source": "DealNews Tools",
      "retailer": "Amazon",
      "category": "Home & Garden",
      "discount": null,
      "date_iso": "2026-07-07T16:51:09-04:00",
      "date_display": "Jul 07, 04:51 PM"
    },
    {
      "id": "DealNews Tools-339767",
      "title": "Husky Liners Floor Mats and Auto Deals at Amazon: Up to 35% off + free shipping",
      "description": "The Husky Liners Amazon storefront features savings of up to 35% off on Husky Liners floor mats, hood protectors, and cargo liners for trucks and SUVs. Most items come backed by an unlimited lifetime ",
      "link": "https://www.dealnews.com/Husky-Liners-Floor-Mats-and-Auto-Deals-at-Amazon-Up-to-35-off-free-shipping/21886308.html?iref=rss-c238",
      "source": "DealNews Tools",
      "retailer": "Amazon",
      "category": "Home & Garden",
      "discount": 35,
      "date_iso": "2026-07-07T16:51:03-04:00",
      "date_display": "Jul 07, 04:51 PM"
    },
    {
      "id": "DealNews-462331",
      "title": "Insignia 85\" QF Series 4K UHD QLED Smart TV for $630 + free shipping",
      "description": "This Insignia 85\" QLED TV is $470 off its regular price of $1,099.99 at Amazon, matching the price at Best Buy direct. It includes Dolby Vision HDR and Dolby Atmos audio support, along with a Voice Re",
      "link": "https://www.dealnews.com/products/Insignia/Insignia-85-QF-Series-4-K-UHD-QLED-Smart-TV/506669.html?iref=rss-c142",
      "source": "DealNews",
      "retailer": "Amazon",
      "category": "Electronics & Tech",
      "discount": 470,
      "date_iso": "2026-07-07T16:38:13-04:00",
      "date_display": "Jul 07, 04:38 PM"
    },
    {
      "id": "DealNews-119517",
      "title": "Roseselsa Wireless Earbuds for $7 + free shipping w/ Prime",
      "description": "Budget wireless earbuds for casual use, and at $7, that's roughly 53% off the $16 list price. Apply coupon code \"ILVF8M7S\" for a savings of $8. Buy Now at Amazon      Features     10mm DLC driver with",
      "link": "https://www.dealnews.com/Roseselsa-Wireless-Earbuds-for-7-free-shipping-w-Prime/21871392.html?iref=rss-c142",
      "source": "DealNews",
      "retailer": "Amazon",
      "category": "Electronics & Tech",
      "discount": 53,
      "date_iso": "2026-07-07T16:37:07-04:00",
      "date_display": "Jul 07, 04:37 PM"
    },
    {
      "id": "DealNews-333244",
      "title": "EcoFlow Power Station & Solar Panel Deals at eBay: Up to 45% off + shipping varies",
      "description": "Use promo code \"EFJULYSALE20\" for an extra 20% off at the EcoFlow Official Store on eBay, with a maximum discount of $500. Most products are certified refurbished and include an Allstate warranty. Som",
      "link": "https://www.dealnews.com/Eco-Flow-Power-Station-Solar-Panel-Deals-at-eBay-Up-to-45-off-shipping-varies/21886266.html?iref=rss-c142",
      "source": "DealNews",
      "retailer": "Various",
      "category": "Electronics & Tech",
      "discount": 45,
      "date_iso": "2026-07-07T14:48:56-04:00",
      "date_display": "Jul 07, 02:48 PM"
    },
    {
      "id": "DealNews Tools-615861",
      "title": "Botslab 4K 3-Channel Dash Cam for $120 + free shipping",
      "description": "The Botslab G980H records front, rear, and interior simultaneously in 4K, which suits rideshare drivers or anyone who wants full-coverage footage without running multiple cameras. Apply coupon code \"G",
      "link": "https://www.dealnews.com/products/Botslab/Botslab-4-K-3-Channel-Dash-Cam/498923.html?iref=rss-c238",
      "source": "DealNews Tools",
      "retailer": "Amazon",
      "category": "Home & Garden",
      "discount": null,
      "date_iso": "2026-07-07T13:12:38-04:00",
      "date_display": "Jul 07, 01:12 PM"
    },
    {
      "id": "DealNews-859555",
      "title": "Refurb Unlocked Samsung Galaxy S24 Ultra 256GB Smartphone for $528 + free shipping",
      "description": "The refurbished Unlocked Samsung Galaxy S24 Ultra is $527.99 right now at eBay. Select customers might see an extra $20 off promo code if they check out with Klarna. It comes with 256GB of storage, 12",
      "link": "https://www.dealnews.com/products/Samsung/Unlocked-Samsung-Galaxy-S24-Ultra-256-GB-Smartphone/478349.html?iref=rss-c142",
      "source": "DealNews",
      "retailer": "Various",
      "category": "Electronics & Tech",
      "discount": 20,
      "date_iso": "2026-07-07T12:42:23-04:00",
      "date_display": "Jul 07, 12:42 PM"
    },
    {
      "id": "DealNews Tools-968008",
      "title": "Wolfbox Car Windshield Sun Shade for Tesla Model 3 and Model Y for $17 + free shipping w/ Prime",
      "description": "Blocks heat and UV from the large front windshield on Model 3 and Model Y, which have notably more glass exposure than most sedans. Apply coupon code \"CIR5DJOJ\" for a savings of $19. Buy Now at Amazon",
      "link": "https://www.dealnews.com/Wolfbox-Car-Windshield-Sun-Shade-for-Tesla-Model-3-and-Model-Y-for-17-free-shipping-w-Prime/21867071.html?iref=rss-c238",
      "source": "DealNews Tools",
      "retailer": "Amazon",
      "category": "Home & Garden",
      "discount": null,
      "date_iso": "2026-07-07T12:40:13-04:00",
      "date_display": "Jul 07, 12:40 PM"
    },
    {
      "id": "DealNews Tools-945863",
      "title": "TuTrackAI OBD 4G LTE GPS Vehicle Tracker for $77 + free shipping",
      "description": "A plug-and-play OBD port tracker with a built-in SIM and no ongoing subscription fees, which makes it worth a look if you want basic vehicle tracking without committing to a monthly plan. Clip the on-",
      "link": "https://www.dealnews.com/products/Tu-Track-AI/Tu-Track-AI-OBD-4-G-LTE-GPS-Vehicle-Tracker/499256.html?iref=rss-c238",
      "source": "DealNews Tools",
      "retailer": "Amazon",
      "category": "Home & Garden",
      "discount": null,
      "date_iso": "2026-07-07T11:31:35-04:00",
      "date_display": "Jul 07, 11:31 AM"
    },
    {
      "id": "DealNews-667054",
      "title": "Granicell AAA Rechargeable Batteries 16-Pack for $10 + free shipping w/ Prime",
      "description": "Rechargeable AAA batteries in a 16-pack work well for households running multiple devices like remotes, flashlights, or kids' toys. Apply coupon code \"RG84UCCI\" for a savings of $10. Buy Now at Amazon",
      "link": "https://www.dealnews.com/products/Granicell/Granicell-AAA-Rechargeable-Batteries-16-Pack/506661.html?iref=rss-c142",
      "source": "DealNews",
      "retailer": "Amazon",
      "category": "Electronics & Tech",
      "discount": null,
      "date_iso": "2026-07-07T11:06:34-04:00",
      "date_display": "Jul 07, 11:06 AM"
    },
    {
      "id": "DealNews-295296",
      "title": "Veektomx 10,000mAh Mini Portable Power Bank for $12 + free shipping w/ Prime",
      "description": "Compact enough to fit in a pocket and capable of fully charging most smartphones twice over, this is a practical option for travelers, commuters, or anyone who regularly runs low before finding an out",
      "link": "https://www.dealnews.com/products/Veektomx/Veektomx-10-000-m-Ah-Mini-Portable-Power-Bank/506659.html?iref=rss-c142",
      "source": "DealNews",
      "retailer": "Amazon",
      "category": "Electronics & Tech",
      "discount": null,
      "date_iso": "2026-07-07T10:26:45-04:00",
      "date_display": "Jul 07, 10:26 AM"
    },
    {
      "id": "DealNews-357849",
      "title": "Aimiler Level 2 48A WiFi EV Charger for $130 + free shipping",
      "description": "This is a Level 2 unit with a 48A output, which is on the higher end for home chargers and will charge most EVs faster than the more common 32A or 40A options. Apply coupon code \"2HDLVAN2\" for an extr",
      "link": "https://www.dealnews.com/products/Aimiler/Aimiler-Level-2-48-A-Wi-Fi-EV-Charger/506658.html?iref=rss-c142",
      "source": "DealNews",
      "retailer": "Amazon",
      "category": "Electronics & Tech",
      "discount": null,
      "date_iso": "2026-07-07T10:16:33-04:00",
      "date_display": "Jul 07, 10:16 AM"
    },
    {
      "id": "DealNews-008247",
      "title": "Apple Accessories at Target:  Up to 20% off  + free shipping",
      "description": "Save on Apple accessories including MagSafe chargers, Magic Keyboards, iPhone cases, and more. Shipping adds $6.99, but orders of $35 or more qualify for free shipping. (Pickup may also be available, ",
      "link": "https://www.dealnews.com/Apple-Accessories-at-Target-Up-to-20-off-free-shipping/21886156.html?iref=rss-c142",
      "source": "DealNews",
      "retailer": "Target",
      "category": "Electronics & Tech",
      "discount": 20,
      "date_iso": "2026-07-07T09:19:48-04:00",
      "date_display": "Jul 07, 09:19 AM"
    },
    {
      "id": "DealNews-075881",
      "title": "JLab JBuds Party Portable Bluetooth Speaker for $31 + free shipping",
      "description": "At Amazon, get the JLab JBuds Party Portable Bluetooth Speaker for $31. It's the best deal we could find by $14. It's IP56 rated against water jets and dust, and it can play for up to 12 hours on a ch",
      "link": "https://www.dealnews.com/JLab-JBuds-Party-Portable-Bluetooth-Speaker-for-31-free-shipping/21886154.html?iref=rss-c142",
      "source": "DealNews",
      "retailer": "Amazon",
      "category": "Electronics & Tech",
      "discount": null,
      "date_iso": "2026-07-07T09:12:19-04:00",
      "date_display": "Jul 07, 09:12 AM"
    },
    {
      "id": "DealNews-924323",
      "title": "Amazon Resale Cameras: Deals on open-box and refurbs + free shipping w/ Prime",
      "description": "In this sale you can get deals on a selection of refurbished and open-box digital cameras, security cameras, and accessories. These items in the Amazon Resale section are returns that have been put th",
      "link": "https://www.dealnews.com/Amazon-Resale-Cameras-Deals-on-open-box-and-refurbs-free-shipping-w-Prime/21886150.html?iref=rss-c142",
      "source": "DealNews",
      "retailer": "Amazon",
      "category": "Electronics & Tech",
      "discount": null,
      "date_iso": "2026-07-07T09:05:23-04:00",
      "date_display": "Jul 07, 09:05 AM"
    },
    {
      "id": "DealNews Tools-405275",
      "title": "4-Piece Precision Hook and Pick Set for $2 + free shipping w/ $25",
      "description": "At Amazon Haul, get this 4-Piece Precision Hook and Pick Set for $2.08. It's the best deal we could find by $2. Shipping is free on Amazon Haul orders of $25 or more. Buy Now at Amazon",
      "link": "https://www.dealnews.com/4-Piece-Precision-Hook-and-Pick-Set-for-2-free-shipping-w-25/21886097.html?iref=rss-c238",
      "source": "DealNews Tools",
      "retailer": "Amazon",
      "category": "Home & Garden",
      "discount": null,
      "date_iso": "2026-07-07T06:40:00-04:00",
      "date_display": "Jul 07, 06:40 AM"
    },
    {
      "id": "DealNews Tools-204671",
      "title": "Wireless CarPlay & Android Auto Adapter for $102 + free shipping",
      "description": "At Amazon, get this Wireless CarPlay & Android Auto Adapter for $102 when you clip the on-page coupon. It's the best price Amazon has charged for this model. It upgrades a factory wired CarPlay or And",
      "link": "https://www.dealnews.com/Wireless-Car-Play-Android-Auto-Adapter-for-102-free-shipping/21886071.html?iref=rss-c238",
      "source": "DealNews Tools",
      "retailer": "Amazon",
      "category": "Home & Garden",
      "discount": null,
      "date_iso": "2026-07-07T05:29:54-04:00",
      "date_display": "Jul 07, 05:29 AM"
    },
    {
      "id": "DealNews Tools-951068",
      "title": "Aegis Mats 7.9x16-Foot Garage Floor Mat for $80 + free shipping",
      "description": "At Amazon, get the Aegis Mats 7.9x16-Foot Garage Floor Mat for $80 when you clip the on-page coupon. It's the best deal Amazon has offered for this garage floor mat. It's made from heavy-duty 610GSM P",
      "link": "https://www.dealnews.com/Aegis-Mats-7-9-x16-Foot-Garage-Floor-Mat-for-80-free-shipping/21886017.html?iref=rss-c238",
      "source": "DealNews Tools",
      "retailer": "Amazon",
      "category": "Home & Garden",
      "discount": null,
      "date_iso": "2026-07-07T02:52:47-04:00",
      "date_display": "Jul 07, 02:52 AM"
    },
    {
      "id": "DealNews Tools-287765",
      "title": "Xprite Motorcycle RGB LED Light Kit for $20 + free shipping w/ Prime",
      "description": "Amazon offers the Xprite Motorcycle RGB LED Light Kit for $19.99.\u00a0 That's half what you'd pay elsewhere and its best-ever price.\u00a0 Shipping is free for Prime members. Buy Now at Amazon",
      "link": "https://www.dealnews.com/products/Xprite-Motorcycle-RGB-LED-Light-Kit/506329.html?iref=rss-c238",
      "source": "DealNews Tools",
      "retailer": "Amazon",
      "category": "Home & Garden",
      "discount": null,
      "date_iso": "2026-07-06T21:12:47-04:00",
      "date_display": "Jul 06, 09:12 PM"
    },
    {
      "id": "DealNews Tools-118216",
      "title": "Lenoma Motion Sensor RV Step Light for $10 + free shipping w/ Prime",
      "description": "Small LED step lights designed to illuminate RV entry stairs at night, which makes them useful for anyone who camps in low-light conditions or moves around the rig after dark. At $10, that's 50% off t",
      "link": "https://www.dealnews.com/products/Lenoma/Lenoma-Motion-Sensor-RV-Step-Light/506313.html?iref=rss-c238",
      "source": "DealNews Tools",
      "retailer": "Amazon",
      "category": "Home & Garden",
      "discount": 50,
      "date_iso": "2026-07-06T11:13:35-04:00",
      "date_display": "Jul 06, 11:13 AM"
    },
    {
      "id": "DealNews Tools-812377",
      "title": "Purolator PurolatorONE Advanced Engine Air Filter for $6 + free shipping w/ Prime",
      "description": "At Amazon, get the Purolator PurolatorONE Advanced Engine Air Filter for $6.48. It's the best price we could find by $2. It uses multi-fiber, high-density media rated to trap 99% of contaminants and d",
      "link": "https://www.dealnews.com/Purolator-Purolator-ONE-Advanced-Engine-Air-Filter-for-6-free-shipping-w-Prime/21883327.html?iref=rss-c238",
      "source": "DealNews Tools",
      "retailer": "Amazon",
      "category": "Home & Garden",
      "discount": null,
      "date_iso": "2026-07-06T04:08:46-04:00",
      "date_display": "Jul 06, 04:08 AM"
    },
    {
      "id": "DealNews Tools-566439",
      "title": "Rightline Gear Moki Ascent Folding Door Step for $31 + free shipping",
      "description": "Amazon offers the Rightline Gear Moki Ascent Folding Door Step for $31.14.\u00a0 That's a $4 low.\u00a0 Shipping is free. Buy Now at Amazon      Features     400-lb. capacity",
      "link": "https://www.dealnews.com/products/Rightline-Gear/Rightline-Gear-Moki-Ascent-Folding-Door-Step/505940.html?iref=rss-c238",
      "source": "DealNews Tools",
      "retailer": "Amazon",
      "category": "Home & Garden",
      "discount": null,
      "date_iso": "2026-07-05T21:32:17-04:00",
      "date_display": "Jul 05, 09:32 PM"
    },
    {
      "id": "DealNews Tools-250025",
      "title": "Munchkin Brica Magnetic Stretch to Fit Sun Shade for $10 + free shipping w/ Prime",
      "description": "Amazon offers the Munchkin Brica Magnetic Stretch to Fit Sun Shade for $10.07, its best-ever price.\u00a0 Shipping is free for Prime members.\u00a0 Alternately, get this Munchkin Brica roller shade 2-pack for $",
      "link": "https://www.dealnews.com/products/Munchkin/Munchkin-Brica-Magnetic-Stretch-to-Fit-Sun-Shade/475697.html?iref=rss-c238",
      "source": "DealNews Tools",
      "retailer": "Amazon",
      "category": "Home & Garden",
      "discount": null,
      "date_iso": "2026-07-05T20:59:38-04:00",
      "date_display": "Jul 05, 08:59 PM"
    },
    {
      "id": "DealNews-272900",
      "title": "Woot Prime Leftovers Sale: Up to 87% off + free shipping w/ Prime",
      "description": "This Woot Prime Leftovers clearance sale runs through July 6 and includes electronics, tools, pet supplies, apparel, and more, discounted as high as 81%. Highlights include the Shure Rycote Shoe Mount",
      "link": "https://www.dealnews.com/Woot-Prime-Leftovers-Sale-Up-to-87-off-free-shipping-w-Prime/21871287.html?iref=rss-c142",
      "source": "DealNews",
      "retailer": "Amazon",
      "category": "Electronics & Tech",
      "discount": 87,
      "date_iso": "2026-07-03T03:30:22-04:00",
      "date_display": "Jul 03, 03:30 AM"
    },
    {
      "id": "DealNews Tools-752567",
      "title": "StarKnightMT Promo Code: 20% off sitewide + free shipping",
      "description": "StarKnightMT takes 20% off sitewide via promo code \"DN20\". Save on aftermarket UTV/ATV parts and accessories, including windshields, doors, seat covers, bumpers, storage boxes and bags, mirrors, mount",
      "link": "https://www.dealnews.com/Star-Knight-MT-Promo-Code-20-off-sitewide-free-shipping/21866635.html?iref=rss-c238",
      "source": "DealNews Tools",
      "retailer": "Various",
      "category": "Home & Garden",
      "discount": 20,
      "date_iso": "2026-07-01T03:38:19-04:00",
      "date_display": "Jul 01, 03:38 AM"
    },
    {
      "id": "DealNews-006773",
      "title": "Woot Extra Discounts Clearance Hub: Up to an extra 70% off + free shipping w/ Prime",
      "description": "Woot\u2019s Discount Hub has several ways to stack savings through July 31. Buy seven or more toys to get 70% off, spend $50 on kitchen appliances and dining items and use code \u201cCHEFTEN\u201d for $10 off, buy t",
      "link": "https://www.dealnews.com/Woot-Extra-Discounts-Clearance-Hub-Up-to-an-extra-70-off-free-shipping-w-Prime/21862595.html?iref=rss-c142",
      "source": "DealNews",
      "retailer": "Amazon",
      "category": "Electronics & Tech",
      "discount": 70,
      "date_iso": "2026-06-29T05:08:45-04:00",
      "date_display": "Jun 29, 05:08 AM"
    }
  ]
}