{
  "updated": "2026-07-06 18:20 UTC",
  "count": 46,
  "deals": [
    {
      "id": "Slickdeals-589260",
      "title": "BOSGAME P3 Mix Mini PC: AMD Ryzen 5 7640HS, 16GB DDR5 RAM, 512GB SSD $358 + Free S&H",
      "description": "BOSGAME Official via Amazon [amazon.com] has *BOSGAME P3 Mix Mini PC, Mini Desktop with Ryzen 7640HS, 16GB DDR5, 512GB PCIe SSD* for *$358*. \n*Shipping is free*. \n \namazon.com/dp/B0FPC7WM2P...",
      "link": "https://slickdeals.net/f/19726455-358-bosgame-p3-mix-mini-pc-mini-desktop-with-ryzen-7640hs-16gb-ddr5-512gb-pcie-ssd-at-amazon?utm_source=rss&utm_content=fp&utm_medium=RSS2",
      "source": "Slickdeals",
      "retailer": "Amazon",
      "category": "Electronics & Tech",
      "discount": null,
      "date_iso": "2026-07-06T17:29:45+00:00",
      "date_display": "Jul 06, 05:29 PM"
    },
    {
      "id": "Slickdeals-580109",
      "title": "Craftsman 3/4\" Manual Cut Bypass Pruner $8.70",
      "description": "Amazon [amazon.com] has *Craftsman 3/4-in. Manual Cut Bypass Pruner* for *$8.70*. \n*Shipping is free* with Prime or on $35+ orders. \n \namazon.com/dp/B0CWH5GKDB [amazon.com] \n \nPlease report the deal..",
      "link": "https://slickdeals.net/f/19726620-8-70-craftsman-3-4-in-manual-cut-bypass-pruner-at-amazon?utm_source=rss&utm_content=fp&utm_medium=RSS2",
      "source": "Slickdeals",
      "retailer": "Amazon",
      "category": "Tools & Hardware",
      "discount": null,
      "date_iso": "2026-07-06T17:21:59+00:00",
      "date_display": "Jul 06, 05:21 PM"
    },
    {
      "id": "Slickdeals-853422",
      "title": "ThermoMaven Upgraded Bristle-Free BBQ Grill Brush w/ 3 Replaceable Heads $20 + Free S&H",
      "description": "ThermoMaven-US via Amazon [amazon.com] has *ThermoMaven Bristle-Free BBQ Grill Brush w/ 3 Replaceable Heads* (Red or Black) for *$19.99* w/ code NJZ44XQL at checkout. *Shipping is...",
      "link": "https://slickdeals.net/f/19727403-thermomaven-upgraded-bristle-free-bbq-grill-brush-w-3-replaceable-heads-20-free-shipping?utm_source=rss&utm_content=fp&utm_medium=RSS2",
      "source": "Slickdeals",
      "retailer": "Amazon",
      "category": "Home & Garden",
      "discount": null,
      "date_iso": "2026-07-06T17:19:37+00:00",
      "date_display": "Jul 06, 05:19 PM"
    },
    {
      "id": "Slickdeals-729652",
      "title": "2-Pk 35-lb Cap Barbell Cast Iron Coated Hex Dumbbells $60.75 + Free S&H",
      "description": "(2 pack) CAP Barbell, 35lb Coated Hex Dumbbell $61 FS @ Walmart \n \nhttps://www.walmart.com/ip/2-pack...5539071746",
      "link": "https://slickdeals.net/f/19719234-2-pack-cap-barbell-35lb-coated-hex-dumbbell-61-fs-walmart?utm_source=rss&utm_content=fp&utm_medium=RSS2",
      "source": "Slickdeals",
      "retailer": "Walmart",
      "category": "Sporting Goods",
      "discount": null,
      "date_iso": "2026-07-06T17:11:18+00:00",
      "date_display": "Jul 06, 05:11 PM"
    },
    {
      "id": "Slickdeals-299042",
      "title": "COMHOMA Big & Tall Ergonomic Gaming/Office Chair w/ Footrest $138 + Free S&H",
      "description": "Verona Sky via Amazon [amazon.com] has *COMHOMA Big & Tall Ergonomic Gaming/Office Chair w/ Footrest, Pocket Spring Lumbar Support & 150\u00b0 Recline *(with Pillow, Faux Leather, Space Black) for $229.99.",
      "link": "https://slickdeals.net/f/19637241-comhoma-big-tall-ergonomic-gaming-office-chair-w-footrest-pocket-spring-lumbar-support-pillow-150-recline-137-99-free-shipping?utm_source=rss&utm_content=fp&utm_medium=RSS2",
      "source": "Slickdeals",
      "retailer": "Amazon",
      "category": "Electronics & Tech",
      "discount": null,
      "date_iso": "2026-07-06T16:59:00+00:00",
      "date_display": "Jul 06, 04:59 PM"
    },
    {
      "id": "Slickdeals-801631",
      "title": "Fanttik S1 Pro Cordless Electric Screwdriver w/ 16 Bits $40 + Free S&H",
      "description": "*Fanttik Innovation Direct via Amazon [amazon.com]* has the *S1 Pro Electric Screwdriver for Furniture & Gaming PC (Max 6 N\u00b7m, 3 Torque Settings, 16 S2 Steel Bits, 2000mAh)* for $49.99 - *$10* coupon.",
      "link": "https://slickdeals.net/f/19648956-fanttik-s1-pro-cordless-electric-screwdriver-w-16-bits-39-99-free-s-h?utm_source=rss&utm_content=fp&utm_medium=RSS2",
      "source": "Slickdeals",
      "retailer": "Amazon",
      "category": "Electronics & Tech",
      "discount": null,
      "date_iso": "2026-07-06T16:44:54+00:00",
      "date_display": "Jul 06, 04:44 PM"
    },
    {
      "id": "Slickdeals-222528",
      "title": "Klein Tools Ratcheting Data Cable Crimper / Cutter + 50-Pk CAT6 RJ45 Data Plugs $50 + Free S&H",
      "description": "Amazon [amazon.com] has *Klein Tools 80024 Ratcheting Data Cable and RJ45 Crimp Tool with CAT6 Plug 50-Pack, Pass Thru Installation Tool Kit* for *$49.97*. \n*Shipping is free*. \n...",
      "link": "https://slickdeals.net/f/19719207-49-97-klein-tools-80024-ratcheting-data-cable-and-rj45-crimp-tool-with-cat6-plug-50-pack-pass-thru-installation-tool-kit-at-amazon?utm_source=rss&utm_content=fp&utm_medium=RSS2",
      "source": "Slickdeals",
      "retailer": "Amazon",
      "category": "Tools & Hardware",
      "discount": null,
      "date_iso": "2026-07-06T16:22:22+00:00",
      "date_display": "Jul 06, 04:22 PM"
    },
    {
      "id": "Slickdeals-478593",
      "title": "75\" Sony 4K Ultra HD BRAVIA 3 LED Smart TV $700 + Free S&H",
      "description": "Amazon.com has Sony 75-Inch Class 4K Ultra HD BRAVIA 3 LED Smart TV with Google TV, Dolby Vision HDR, and Exclusive Features for PlayStation\u00ae5 (K-75S30) for $699.99. \nShipping is free. \n \n...",
      "link": "https://slickdeals.net/f/19720890-sony-75-inch-class-4k-ultra-hd-bravia-3-led-smart-tv-k-75s30-699-99-free-s-h-at-amazon?utm_source=rss&utm_content=fp&utm_medium=RSS2",
      "source": "Slickdeals",
      "retailer": "Amazon",
      "category": "Electronics & Tech",
      "discount": null,
      "date_iso": "2026-07-06T16:06:53+00:00",
      "date_display": "Jul 06, 04:06 PM"
    },
    {
      "id": "Slickdeals-874581",
      "title": "EZVALO 6000mAh LED Rechargeable Camping Lantern $8.40",
      "description": "EZMilestone via Amazon [amazon.com] has EZVALO 6000mAh LED Rechargeable Camping Lantern on sale for *$8.39* w/ code *T9E2VKS6* at checkout. Shipping is free w/ Prime or orders $35+ \n \nProduct...",
      "link": "https://slickdeals.net/f/19717929-ezvalo-6000mah-led-rechargeable-camping-lantern-8-39-free-shipping-w-prime-or-orders-35?utm_source=rss&utm_content=fp&utm_medium=RSS2",
      "source": "Slickdeals",
      "retailer": "Amazon",
      "category": "Outdoor & Lawn",
      "discount": null,
      "date_iso": "2026-07-06T15:46:47+00:00",
      "date_display": "Jul 06, 03:46 PM"
    },
    {
      "id": "Slickdeals-338336",
      "title": "217-Pc LEGO Botanicals: Botanical Collection: Happy Plants $18.40",
      "description": "Amazon [amazon.com] has *217-Piece Lego Botanicals Happy Plants Toy* for *$18.39*. Shipping is free w/ Prime or on $35+. \n \n \nProduct Description from Amazon:[list][*]DELIGHT YOUNG GARDENERS \u2013 Help...",
      "link": "https://slickdeals.net/f/19727514-217-piece-lego-botanicals-happy-plants-toy-18-39-free-shipping-w-prime-or-on-35?utm_source=rss&utm_content=fp&utm_medium=RSS2",
      "source": "Slickdeals",
      "retailer": "Amazon",
      "category": "Home & Garden",
      "discount": null,
      "date_iso": "2026-07-06T15:36:58+00:00",
      "date_display": "Jul 06, 03:36 PM"
    },
    {
      "id": "DealNews-829084",
      "title": "Hiicam 4K Waterproof Action Camera for $42 + free shipping",
      "description": "This action camera is good for casual outdoor use, travel vlogging, or anyone who wants a mountable camera without committing to GoPro pricing. Apply coupon code \"I4GWKXG7\" for a savings of $28. Buy N",
      "link": "https://www.dealnews.com/products/Hiicam/Hiicam-4-K-Waterproof-Action-Camera/506316.html?iref=rss-c142",
      "source": "DealNews",
      "retailer": "Amazon",
      "category": "Electronics & Tech",
      "discount": null,
      "date_iso": "2026-07-06T12:10:34-04:00",
      "date_display": "Jul 06, 12:10 PM"
    },
    {
      "id": "DealNews-817493",
      "title": "Lisen 4-in-1 USB-C / Lightning Retractable Car Charger for $16 + free shipping w/ Prime",
      "description": "This LISEN retractable car charger is $16.12, down from $19.99. It packs 84W of output across a 45W USB-C port and a 12W USB-A port, with two retractable cables that stretch up to 31.5\" so it can char",
      "link": "https://www.dealnews.com/products/Lisen/Lisen-4-in-1-USB-C-Lightning-Retractable-Car-Charger/481312.html?iref=rss-c142",
      "source": "DealNews",
      "retailer": "Amazon",
      "category": "Electronics & Tech",
      "discount": null,
      "date_iso": "2026-07-06T11:53:33-04:00",
      "date_display": "Jul 06, 11:53 AM"
    },
    {
      "id": "DealNews-726201",
      "title": "Hisense E6 Cinema Series 65E6QF 65\" 4K HDR QLED UHD Smart TV for $378 + free shipping",
      "description": "The Hisense 65E6QF is $100 off its regular price of $478 at Amazon and the lowest price we've seen since Black Friday. This 65\" Hi-QLED TV supports both Dolby Vision and Dolby Atmos, along with HDR 10",
      "link": "https://www.dealnews.com/products/Hisense/Hisense-E6-Cinema-Series-65-E6-QF-65-4-K-HDR-QLED-UHD-Smart-TV/494091.html?iref=rss-c142",
      "source": "DealNews",
      "retailer": "Amazon",
      "category": "Electronics & Tech",
      "discount": 100,
      "date_iso": "2026-07-06T11:51:54-04:00",
      "date_display": "Jul 06, 11:51 AM"
    },
    {
      "id": "DealNews-978685",
      "title": "Wegear 100W 3-Port USB C Charger for $20 + free shipping",
      "description": "Useful for anyone juggling multiple devices at once, this 100W foldable 3-port USB-C wall charger handles a laptop, phone, and tablet simultaneously from a single outlet. Apply coupon code \"UBUY76YV\" ",
      "link": "https://www.dealnews.com/products/Wegear/Wegear-100-W-3-Port-USB-C-Charger/506314.html?iref=rss-c142",
      "source": "DealNews",
      "retailer": "Amazon",
      "category": "Electronics & Tech",
      "discount": null,
      "date_iso": "2026-07-06T11:41:44-04:00",
      "date_display": "Jul 06, 11:41 AM"
    },
    {
      "id": "DealNews Tools-765188",
      "title": "Lenoma Motion Sensor RV Step Light for $10 + free shipping w/ Prime",
      "description": "Small LED step lights designed to illuminate RV entry stairs at night, which makes them useful for anyone who camps in low-light conditions or moves around the rig after dark. At $10, that's 50% off t",
      "link": "https://www.dealnews.com/products/Lenoma/Lenoma-Motion-Sensor-RV-Step-Light/506313.html?iref=rss-c238",
      "source": "DealNews Tools",
      "retailer": "Amazon",
      "category": "Home & Garden",
      "discount": 50,
      "date_iso": "2026-07-06T11:13:35-04:00",
      "date_display": "Jul 06, 11:13 AM"
    },
    {
      "id": "DealNews-666944",
      "title": "NUU B30 5G Unlocked Android Smartphone for $150 + free shipping",
      "description": "Get the NUU B30 5G Unlocked Android Smartphone for $60 less than Amazon charges when you buy from Nuu Mobile direct. Shipping is free. Buy Now at Nuu Mobile",
      "link": "https://www.dealnews.com/NUU-B30-5-G-Unlocked-Android-Smartphone-for-150-free-shipping/21864297.html?iref=rss-c142",
      "source": "DealNews",
      "retailer": "Amazon",
      "category": "Electronics & Tech",
      "discount": null,
      "date_iso": "2026-07-06T10:04:30-04:00",
      "date_display": "Jul 06, 10:04 AM"
    },
    {
      "id": "DealNews-321271",
      "title": "Tiffen Multicoated UV Protection Filters  for From $14  +  free shipping",
      "description": "Today only, as one of its daily deals in its Deal Zone, B&H offers select Tiffen Multicoated UV Protection Filters starting at $13.99. That's up to 53% off, with the 49mm, 52mm, 55mm, and 58mm sizes a",
      "link": "https://www.dealnews.com/Tiffen-Multicoated-UV-Protection-Filters-for-From-14-free-shipping/21883436.html?iref=rss-c142",
      "source": "DealNews",
      "retailer": "Various",
      "category": "Electronics & Tech",
      "discount": 53,
      "date_iso": "2026-07-06T09:02:54-04:00",
      "date_display": "Jul 06, 09:02 AM"
    },
    {
      "id": "DealNews-619704",
      "title": "Joby Wavo Lav Pro Lavalier Microphone  for $20 +  free shipping",
      "description": "Today only, as one of its daily deals in its Deal Zone, B&H offers the JOBY Wavo Lav PRO Lavalier Microphone for $19.95. That's a savings of $90 off the $109.95 list price. Designed for interviews, Yo",
      "link": "https://www.dealnews.com/Joby-Wavo-Lav-Pro-Lavalier-Microphone-for-20-free-shipping/21883431.html?iref=rss-c142",
      "source": "DealNews",
      "retailer": "Various",
      "category": "Electronics & Tech",
      "discount": 90,
      "date_iso": "2026-07-06T08:56:24-04:00",
      "date_display": "Jul 06, 08:56 AM"
    },
    {
      "id": "DealNews-582035",
      "title": "JLab JBuds Lux ANC Over-Ear Headphones for $45 + free shipping",
      "description": "At Amazon, get the JLab JBuds Lux ANC Over-Ear Headphones for $45. It's the best price we could find by $35. The over-ear design includes hybrid ANC that blocks up to 35 dB of noise, Bluetooth multipo",
      "link": "https://www.dealnews.com/JLab-JBuds-Lux-ANC-Over-Ear-Headphones-for-45-free-shipping/21883423.html?iref=rss-c142",
      "source": "DealNews",
      "retailer": "Amazon",
      "category": "Electronics & Tech",
      "discount": null,
      "date_iso": "2026-07-06T08:45:08-04:00",
      "date_display": "Jul 06, 08:45 AM"
    },
    {
      "id": "DealNews-970233",
      "title": "Roseselsa Wireless Earbuds for $7 + free shipping w/ Prime",
      "description": "Budget wireless earbuds for casual use, and at $7, that's roughly 53% off the $16 list price. Apply coupon code \"ILVF8M7S\" for a savings of $8. Buy Now at Amazon      Features     10mm DLC driver with",
      "link": "https://www.dealnews.com/Roseselsa-Wireless-Earbuds-for-7-free-shipping-w-Prime/21871392.html?iref=rss-c142",
      "source": "DealNews",
      "retailer": "Amazon",
      "category": "Electronics & Tech",
      "discount": 53,
      "date_iso": "2026-07-06T08:31:11-04:00",
      "date_display": "Jul 06, 08:31 AM"
    },
    {
      "id": "DealNews-048730",
      "title": "JBL Headphones and Speakers at Macy's: Up to 47% off + free shipping w/ $39",
      "description": "This JBL electronics sale at Macy's includes the Live Pro 2 true wireless earbuds at $89.95, down from $169.95, and the Tune 670NC on-ear Bluetooth headphones at $59.95, down from $109.95. The Tour On",
      "link": "https://www.dealnews.com/JBL-Headphones-and-Speakers-at-Macys-Up-to-47-off-free-shipping-w-39/21883412.html?iref=rss-c142",
      "source": "DealNews",
      "retailer": "Various",
      "category": "Electronics & Tech",
      "discount": 47,
      "date_iso": "2026-07-06T08:22:36-04:00",
      "date_display": "Jul 06, 08:22 AM"
    },
    {
      "id": "DealNews-831876",
      "title": "Open-Box Unlocked Cell Phones at Best Buy: Up to 40% off + free shipping",
      "description": "The price of open-box Android phones starts $46 and iPhones at $416 in the Best Buy Outlet. They're all brand-new but just won't ship in their original packaging. Warranty information is available on ",
      "link": "https://www.dealnews.com/Open-Box-Unlocked-Cell-Phones-at-Best-Buy-Up-to-40-off-free-shipping/21883397.html?iref=rss-c142",
      "source": "DealNews",
      "retailer": "Best Buy",
      "category": "Electronics & Tech",
      "discount": 40,
      "date_iso": "2026-07-06T07:32:17-04:00",
      "date_display": "Jul 06, 07:32 AM"
    },
    {
      "id": "DealNews-457238",
      "title": "Meifigno 360\u00b0 Rotating Magnetic Car Mount for Tesla for $10 + free shipping w/ Prime",
      "description": "Meifigno's 360\u00b0 rotating magnetic car mount is designed specifically for Tesla's interior, which lacks a traditional vent or dashboard lip to clip onto, making a Tesla-specific solution more useful th",
      "link": "https://www.dealnews.com/Meifigno-360-Rotating-Magnetic-Car-Mount-for-Tesla-for-10-free-shipping-w-Prime/21883393.html?iref=rss-c142",
      "source": "DealNews",
      "retailer": "Amazon",
      "category": "Electronics & Tech",
      "discount": 30,
      "date_iso": "2026-07-06T07:26:10-04:00",
      "date_display": "Jul 06, 07:26 AM"
    },
    {
      "id": "DealNews-114161",
      "title": "Open-Box TVs at Best Buy: Up to 50% off + free shipping",
      "description": "Nearly 40 open-box TVs are discounted at Best Buy, with prices starting at $182. These ship free. Pictured is the Open-Box Samsung QN70F 65\" 4K HDR 120Hz Vision AI Neo QLED UHD Smart TV for $702 ($898",
      "link": "https://www.dealnews.com/Open-Box-TVs-at-Best-Buy-Up-to-50-off-free-shipping/21883392.html?iref=rss-c142",
      "source": "DealNews",
      "retailer": "Best Buy",
      "category": "Electronics & Tech",
      "discount": 50,
      "date_iso": "2026-07-06T07:21:28-04:00",
      "date_display": "Jul 06, 07:21 AM"
    },
    {
      "id": "DealNews-186413",
      "title": "Best Buy Outlet Clearance: Up to 95% off + free shipping",
      "description": "You can take up to 95% off clearance, open-box, and refurbished items in the Best Buy Outlet today. Open-box laptops start at just $299, open-box headphones at $89, and TVs are up to 50% off. Most wil",
      "link": "https://www.dealnews.com/Best-Buy-Outlet-Clearance-Up-to-95-off-free-shipping/21883389.html?iref=rss-c142",
      "source": "DealNews",
      "retailer": "Best Buy",
      "category": "Electronics & Tech",
      "discount": 95,
      "date_iso": "2026-07-06T07:09:41-04:00",
      "date_display": "Jul 06, 07:09 AM"
    },
    {
      "id": "DealNews-734219",
      "title": "Sony Headphones Deals at Best Buy: Up to 60% off + free shipping",
      "description": "At Best Buy, select Sony headphones are discounted by up to 60%. Options start as low as $10. My Best Buy members get free shipping. (It's free to join. Shipping is free for everyone over $35. Pickup ",
      "link": "https://www.dealnews.com/Sony-Headphones-Deals-at-Best-Buy-Up-to-60-off-free-shipping/21883375.html?iref=rss-c142",
      "source": "DealNews",
      "retailer": "Best Buy",
      "category": "Electronics & Tech",
      "discount": 60,
      "date_iso": "2026-07-06T06:22:57-04:00",
      "date_display": "Jul 06, 06:22 AM"
    },
    {
      "id": "DealNews Tools-785720",
      "title": "Purolator PurolatorONE Advanced Engine Air Filter for $6 + free shipping w/ Prime",
      "description": "At Amazon, get the Purolator PurolatorONE Advanced Engine Air Filter for $6.48. It's the best price we could find by $2. It uses multi-fiber, high-density media rated to trap 99% of contaminants and d",
      "link": "https://www.dealnews.com/Purolator-Purolator-ONE-Advanced-Engine-Air-Filter-for-6-free-shipping-w-Prime/21883327.html?iref=rss-c238",
      "source": "DealNews Tools",
      "retailer": "Amazon",
      "category": "Home & Garden",
      "discount": null,
      "date_iso": "2026-07-06T04:08:46-04:00",
      "date_display": "Jul 06, 04:08 AM"
    },
    {
      "id": "DealNews-571017",
      "title": "TCL 65QM5K QM5K Series 65\" 4K UHD HDR LED Google TV (2025) for $450 + free shipping",
      "description": "As one of its daily deals, Best Buy offers the TCL 65QM5K QM5K Series 65\" 4K UHD HDR LED Google TV (2025) for $450. That's a savings of 50%. Plus, it ships free. Buy Now at Best Buy      Features     ",
      "link": "https://www.dealnews.com/products/TCL/TCL-65-QM5-K-QM5-K-Series-65-4-K-UHD-HDR-LED-Google-TV-2025/495416.html?iref=rss-c142",
      "source": "DealNews",
      "retailer": "Best Buy",
      "category": "Electronics & Tech",
      "discount": null,
      "date_iso": "2026-07-06T03:50:57-04:00",
      "date_display": "Jul 06, 03:50 AM"
    },
    {
      "id": "DealNews Tools-213493",
      "title": "Rightline Gear Moki Ascent Folding Door Step for $31 + free shipping",
      "description": "Amazon offers the Rightline Gear Moki Ascent Folding Door Step for $31.14.\u00a0 That's a $4 low.\u00a0 Shipping is free. Buy Now at Amazon      Features     400-lb. capacity",
      "link": "https://www.dealnews.com/products/Rightline-Gear/Rightline-Gear-Moki-Ascent-Folding-Door-Step/505940.html?iref=rss-c238",
      "source": "DealNews Tools",
      "retailer": "Amazon",
      "category": "Home & Garden",
      "discount": null,
      "date_iso": "2026-07-05T21:32:17-04:00",
      "date_display": "Jul 05, 09:32 PM"
    },
    {
      "id": "DealNews Tools-880116",
      "title": "Munchkin Brica Magnetic Stretch to Fit Sun Shade for $10 + free shipping w/ Prime",
      "description": "Amazon offers the Munchkin Brica Magnetic Stretch to Fit Sun Shade for $10.07, its best-ever price.\u00a0 Shipping is free for Prime members.\u00a0 Alternately, get this Munchkin Brica roller shade 2-pack for $",
      "link": "https://www.dealnews.com/products/Munchkin/Munchkin-Brica-Magnetic-Stretch-to-Fit-Sun-Shade/475697.html?iref=rss-c238",
      "source": "DealNews Tools",
      "retailer": "Amazon",
      "category": "Home & Garden",
      "discount": null,
      "date_iso": "2026-07-05T20:59:38-04:00",
      "date_display": "Jul 05, 08:59 PM"
    },
    {
      "id": "DealNews Tools-954010",
      "title": "Motor Trend Jumbo Front Windshield Sun Shade for $14 + free shipping w/ Prime",
      "description": "Get the Motor Trend Jumbo Front Windshield Sun Shade in Red for this price at Amazon.\u00a0 That's its best price of the past few years.\u00a0 Shipping is free for Prime members. Buy Now at Amazon      Features",
      "link": "https://www.dealnews.com/products/Motor-Trend/Motor-Trend-Jumbo-Front-Windshield-Sun-Shade/505939.html?iref=rss-c238",
      "source": "DealNews Tools",
      "retailer": "Amazon",
      "category": "Home & Garden",
      "discount": null,
      "date_iso": "2026-07-05T20:31:41-04:00",
      "date_display": "Jul 05, 08:31 PM"
    },
    {
      "id": "DealNews Tools-418936",
      "title": "Wakeman Inflatable Car Mattress for $35 + free shipping",
      "description": "Amazon offers the Wakeman Inflatable Car Mattress for $35.12.\u00a0 That's a $5 low.\u00a0 Shipping is free. Buy Now at Amazon      Features     660-lb. capacity   aux outlet pump   two pillows",
      "link": "https://www.dealnews.com/products/Wakeman/Wakeman-Inflatable-Car-Mattress/482677.html?iref=rss-c238",
      "source": "DealNews Tools",
      "retailer": "Amazon",
      "category": "Home & Garden",
      "discount": null,
      "date_iso": "2026-07-05T20:18:44-04:00",
      "date_display": "Jul 05, 08:18 PM"
    },
    {
      "id": "DealNews Tools-255863",
      "title": "Shine Armor Fortify Quick Coat 8-oz. Ceramic Waterless Detailer Spray for $8.99 via Sub & Save + free shipping w/ Prime",
      "description": "Amazon offers the Shine Armor Fortify Quick Coat 8-oz. Ceramic Waterless Detailer Spray for $8.99 when you subscribe.\u00a0 That's a $6 low.\u00a0 Shipping is free for Prime members. Buy Now at Amazon      Feat",
      "link": "https://www.dealnews.com/Shine-Armor-Fortify-Quick-Coat-8-oz-Ceramic-Waterless-Detailer-Spray-for-8-99-via-Sub-Save-free-shipping-w-Prime/21879135.html?iref=rss-c238",
      "source": "DealNews Tools",
      "retailer": "Amazon",
      "category": "Home & Garden",
      "discount": null,
      "date_iso": "2026-07-05T19:58:11-04:00",
      "date_display": "Jul 05, 07:58 PM"
    },
    {
      "id": "DealNews Tools-719698",
      "title": "Wolfbox Car Windshield Sun Shade for Tesla Model 3 and Model Y for $17 + free shipping w/ Prime",
      "description": "Blocks heat and UV from the large front windshield on Model 3 and Model Y, which have notably more glass exposure than most sedans. Apply coupon code \"CIR5DJOJ\" for a savings of $19. Buy Now at Amazon",
      "link": "https://www.dealnews.com/Wolfbox-Car-Windshield-Sun-Shade-for-Tesla-Model-3-and-Model-Y-for-17-free-shipping-w-Prime/21867071.html?iref=rss-c238",
      "source": "DealNews Tools",
      "retailer": "Amazon",
      "category": "Home & Garden",
      "discount": null,
      "date_iso": "2026-07-05T16:07:56-04:00",
      "date_display": "Jul 05, 04:07 PM"
    },
    {
      "id": "DealNews Tools-491714",
      "title": "Nilight 12-LED Emergency Strobe Dash Light Bar for $15 + free shipping w/ Prime",
      "description": "Amazon offers the Nilight 12-LED Emergency Strobe Dash Light Bar for $14.52.\u00a0 That's a $10 low.\u00a0 Shipping is free for Prime members. Buy Now at Amazon      Features     12 high-intensity LEDs for brig",
      "link": "https://www.dealnews.com/products/Nilight/Nilight-12-LED-Emergency-Strobe-Dash-Light-Bar/505937.html?iref=rss-c238",
      "source": "DealNews Tools",
      "retailer": "Amazon",
      "category": "Home & Garden",
      "discount": null,
      "date_iso": "2026-07-05T15:03:19-04:00",
      "date_display": "Jul 05, 03:03 PM"
    },
    {
      "id": "DealNews Tools-663232",
      "title": "Woot Wireless CarPlay Adapter Deals for From $9.99 + free shipping w/ Prime",
      "description": "This Woot sale discounts three different wireless CarPlay and Android Auto adapters, with prices starting at just $9.99. The priciest one in here is just $12.99, so they're all at great deals, with di",
      "link": "https://www.dealnews.com/Woot-Wireless-Car-Play-Adapter-Deals-for-From-9-99-free-shipping-w-Prime/21875042.html?iref=rss-c238",
      "source": "DealNews Tools",
      "retailer": "Amazon",
      "category": "Home & Garden",
      "discount": null,
      "date_iso": "2026-07-04T02:43:47-04:00",
      "date_display": "Jul 04, 02:43 AM"
    },
    {
      "id": "DealNews Tools-291212",
      "title": "Fortune Perfectus FSR602 All Season 175/65R15 84H Passenger Tire for $50 + free shipping",
      "description": "This Fortune Perfectus FSR602 tire, the item pictured, is priced at $50, down from $110 at Walmart. That's a lower price than several similar 175/65R15 all-season tires on the same page, including the",
      "link": "https://www.dealnews.com/Fortune-Perfectus-FSR602-All-Season-175-65-R15-84-H-Passenger-Tire-for-50-free-shipping/21871414.html?iref=rss-c238",
      "source": "DealNews Tools",
      "retailer": "Walmart",
      "category": "Home & Garden",
      "discount": null,
      "date_iso": "2026-07-03T10:32:01-04:00",
      "date_display": "Jul 03, 10:32 AM"
    },
    {
      "id": "DealNews Tools-346192",
      "title": "5 Plus 26\" and 20\" Windshield Wiper Blades for $9.49 via Sub & Save + free shipping w/ Prime",
      "description": "At Amazon, get the 5 Plus 26\" and 20\" Windshield Wiper Blades for $9.49 when you checkout via Sub & Save. You'd pay $7 more elsewhere. Prime members get free shipping. Buy Now at Amazon",
      "link": "https://www.dealnews.com/5-Plus-26-and-20-Windshield-Wiper-Blades-for-9-49-via-Sub-Save-free-shipping-w-Prime/21871304.html?iref=rss-c238",
      "source": "DealNews Tools",
      "retailer": "Amazon",
      "category": "Home & Garden",
      "discount": null,
      "date_iso": "2026-07-03T04:20:35-04:00",
      "date_display": "Jul 03, 04:20 AM"
    },
    {
      "id": "DealNews-541279",
      "title": "Woot Prime Leftovers Sale: Up to 87% off + free shipping w/ Prime",
      "description": "This Woot Prime Leftovers clearance sale runs through July 6 and includes electronics, tools, pet supplies, apparel, and more, discounted as high as 81%. Highlights include the Shure Rycote Shoe Mount",
      "link": "https://www.dealnews.com/Woot-Prime-Leftovers-Sale-Up-to-87-off-free-shipping-w-Prime/21871287.html?iref=rss-c142",
      "source": "DealNews",
      "retailer": "Amazon",
      "category": "Electronics & Tech",
      "discount": 87,
      "date_iso": "2026-07-03T03:30:22-04:00",
      "date_display": "Jul 03, 03:30 AM"
    },
    {
      "id": "DealNews Tools-939698",
      "title": "Ring Sensors Car Alarm for $40 + free shipping",
      "description": "This Ring car alarm is $10 off its regular price and matches the all-time low on Amazon. It plugs into a vehicle's OBD-II port with no tools or wiring, draws power from the car while driving, and incl",
      "link": "https://www.dealnews.com/Ring-Sensors-Car-Alarm-for-40-free-shipping/21867222.html?iref=rss-c238",
      "source": "DealNews Tools",
      "retailer": "Amazon",
      "category": "Home & Garden",
      "discount": 10,
      "date_iso": "2026-07-02T20:43:47-04:00",
      "date_display": "Jul 02, 08:43 PM"
    },
    {
      "id": "DealNews Tools-310330",
      "title": "Prestone Antifreeze & Coolant Tester for $4 + free shipping w/ $35",
      "description": "Walmart offers the Prestone Antifreeze & Coolant Tester for $3.97.\u00a0 You'd pay around double elsewhere.\u00a0 Choose pickup or spend $35 to avoid the $6.99 shipping charge. Buy Now at Walmart      Features ",
      "link": "https://www.dealnews.com/Prestone-Antifreeze-Coolant-Tester-for-4-free-shipping-w-35/21867200.html?iref=rss-c238",
      "source": "DealNews Tools",
      "retailer": "Walmart",
      "category": "Home & Garden",
      "discount": null,
      "date_iso": "2026-07-02T18:29:28-04:00",
      "date_display": "Jul 02, 06:29 PM"
    },
    {
      "id": "DealNews Tools-440549",
      "title": "ETENWOLF T300 3-200 PSI Digital Tire Pressure Gauge for $7 + free shipping w/ Prime",
      "description": "This tire pressure gauge (in Orange) is $6.99 at Amazon. It's the best price we found by a buck. Shipping is free for Prime members.\u00a0 Buy Now at Amazon      Features     Pressure range: 3-200 PSI   AN",
      "link": "https://www.dealnews.com/products/Etenwolf/ETENWOLF-T300-3-200-PSI-Digital-Tire-Pressure-Gauge/503768.html?iref=rss-c238",
      "source": "DealNews Tools",
      "retailer": "Amazon",
      "category": "Home & Garden",
      "discount": null,
      "date_iso": "2026-07-02T12:59:24-04:00",
      "date_display": "Jul 02, 12:59 PM"
    },
    {
      "id": "DealNews Tools-617043",
      "title": "Etenwolf 16-Piece Flat Tire Repair Kit for $10 + free shipping w/ Prime",
      "description": "This 16-Piece Flat Tire Repair Kit is $9.98 at Amazon. It's the best price we found by $2. Shipping is free for Prime members.\u00a0 Buy Now at Amazon      Features     16-piece kit   Includes 5x 0.14\" and",
      "link": "https://www.dealnews.com/products/Etenwolf/Etenwolf-16-Piece-Flat-Tire-Repair-Kit/503767.html?iref=rss-c238",
      "source": "DealNews Tools",
      "retailer": "Amazon",
      "category": "Home & Garden",
      "discount": null,
      "date_iso": "2026-07-02T12:48:32-04:00",
      "date_display": "Jul 02, 12:48 PM"
    },
    {
      "id": "DealNews Tools-736847",
      "title": "9x22-Foot Garage Floor Parking Mat  for $104 + free shipping",
      "description": "Amazon offers this  9x22-Foot Garage Floor Parking Mat for $104.That's a savings of $26 and the lowest price we've seen for it. Shipping is free. Buy Now at Amazon",
      "link": "https://www.dealnews.com/9-x22-Foot-Garage-Floor-Parking-Mat-for-104-free-shipping/21867010.html?iref=rss-c238",
      "source": "DealNews Tools",
      "retailer": "Amazon",
      "category": "Home & Garden",
      "discount": null,
      "date_iso": "2026-07-02T05:17:12-04:00",
      "date_display": "Jul 02, 05:17 AM"
    },
    {
      "id": "DealNews Tools-210888",
      "title": "StarKnightMT Promo Code: 20% off sitewide + free shipping",
      "description": "StarKnightMT takes 20% off sitewide via promo code \"DN20\". Save on aftermarket UTV/ATV parts and accessories, including windshields, doors, seat covers, bumpers, storage boxes and bags, mirrors, mount",
      "link": "https://www.dealnews.com/Star-Knight-MT-Promo-Code-20-off-sitewide-free-shipping/21866635.html?iref=rss-c238",
      "source": "DealNews Tools",
      "retailer": "Various",
      "category": "Home & Garden",
      "discount": 20,
      "date_iso": "2026-07-01T03:38:19-04:00",
      "date_display": "Jul 01, 03:38 AM"
    },
    {
      "id": "DealNews-731798",
      "title": "Woot Extra Discounts Clearance Hub: Up to an extra 70% off + free shipping w/ Prime",
      "description": "Woot\u2019s Discount Hub has several ways to stack savings through July 31. Buy seven or more toys to get 70% off, spend $50 on kitchen appliances and dining items and use code \u201cCHEFTEN\u201d for $10 off, buy t",
      "link": "https://www.dealnews.com/Woot-Extra-Discounts-Clearance-Hub-Up-to-an-extra-70-off-free-shipping-w-Prime/21862595.html?iref=rss-c142",
      "source": "DealNews",
      "retailer": "Amazon",
      "category": "Electronics & Tech",
      "discount": 70,
      "date_iso": "2026-06-29T05:08:45-04:00",
      "date_display": "Jun 29, 05:08 AM"
    }
  ]
}